per_datasets/__init__.py
per_datasets/cli.py
per_datasets/reservoir/__init__.py
per_datasets/reservoir/load.py
per_datasets/reservoir/load_random.py
per_datasets/talkaholic/__init__.py
per_datasets/talkaholic/reservoir.py
per_datasets/utils/__init__.py
per_datasets/utils/api.py
per_datasets/utils/config.py
per_datasets/utils/display.py
per_datasets/utils/init.py
per_datasets-0.1.23.dist-info/METADATA
per_datasets-0.1.23.dist-info/WHEEL
per_datasets-0.1.23.dist-info/entry_points.txt
per_datasets-0.1.23.dist-info/top_level.txt
per_datasets-0.1.23.dist-info/RECORD
