Metadata-Version: 2.4
Name: per-datasets
Version: 0.1.23
Summary: A Python package for loading petroleum datasets
Author-email: PERD Team <support@perd.example.com>
License-Expression: MIT
Project-URL: Homepage, https://github.com/P-E-R-D/library-py
Project-URL: Bug Tracker, https://github.com/P-E-R-D/library-py/issues
Classifier: Development Status :: 3 - Alpha
Classifier: Intended Audience :: Developers
Classifier: Intended Audience :: Science/Research
Classifier: Operating System :: OS Independent
Classifier: Programming Language :: Python :: 3
Classifier: Programming Language :: Python :: 3.8
Classifier: Programming Language :: Python :: 3.9
Classifier: Programming Language :: Python :: 3.10
Classifier: Programming Language :: Python :: 3.11
Classifier: Topic :: Scientific/Engineering
Classifier: Topic :: Software Development :: Libraries :: Python Modules
Requires-Python: >=3.8
Requires-Dist: requests>=2.25.1
Requires-Dist: pandas>=1.3.0
Requires-Dist: typing-extensions>=3.10.0.2; python_version < "3.10"
Provides-Extra: dev
Requires-Dist: pytest>=6.0; extra == "dev"
Requires-Dist: pytest-cov>=2.0; extra == "dev"
